<annotation>
	<folder>train</folder>
	<filename>IMG_20191118_115941.jpg</filename>
	<path>/home/gonza/Proyectos/Reconocimiento/2020/object_detection/models/research/object_detection/images/train/IMG_20191118_115941.jpg</path>
	<source>
		<database>Unknown</database>
	</source>
	<size>
		<width>800</width>
		<height>600</height>
		<depth>3</depth>
	</size>
	<segmented>0</segmented>
	<object>
		<name>calculadora</name>
		<pose>Unspecified</pose>
		<truncated>0</truncated>
		<difficult>0</difficult>
		<bndbox>
			<xmin>54</xmin>
			<ymin>165</ymin>
			<xmax>357</xmax>
			<ymax>325</ymax>
		</bndbox>
	</object>
	<object>
		<name>regla</name>
		<pose>Unspecified</pose>
		<truncated>0</truncated>
		<difficult>0</difficult>
		<bndbox>
			<xmin>228</xmin>
			<ymin>32</ymin>
			<xmax>602</xmax>
			<ymax>130</ymax>
		</bndbox>
	</object>
	<object>
		<name>encendedor</name>
		<pose>Unspecified</pose>
		<truncated>1</truncated>
		<difficult>0</difficult>
		<bndbox>
			<xmin>675</xmin>
			<ymin>184</ymin>
			<xmax>800</xmax>
			<ymax>263</ymax>
		</bndbox>
	</object>
	<object>
		<name>lapicera</name>
		<pose>Unspecified</pose>
		<truncated>1</truncated>
		<difficult>0</difficult>
		<bndbox>
			<xmin>608</xmin>
			<ymin>337</ymin>
			<xmax>664</xmax>
			<ymax>600</ymax>
		</bndbox>
	</object>
	<object>
		<name>corrector</name>
		<pose>Unspecified</pose>
		<truncated>0</truncated>
		<difficult>0</difficult>
		<bndbox>
			<xmin>419</xmin>
			<ymin>271</ymin>
			<xmax>603</xmax>
			<ymax>498</ymax>
		</bndbox>
	</object>
</annotation>
